auditory_models/__init__.py
auditory_models/gpsmq/__init__.py
auditory_models/gpsmq/gpsmq.py
auditory_models/helpers/__init__.py
auditory_models/helpers/filterbank.py
auditory_models/helpers/utils.py
auditory_models/stoi/__init__.py
auditory_models/stoi/stoi.py
auditory_models-0.1.1.dist-info/licenses/COPYING
auditory_models-0.1.1.dist-info/METADATA
auditory_models-0.1.1.dist-info/WHEEL
auditory_models-0.1.1.dist-info/top_level.txt
auditory_models-0.1.1.dist-info/RECORD
