Metadata-Version: 2.4
Name: auditory_models
Version: 0.1.1
Summary: Computation of auditory models
Author-email: Max Zimmermann <max.zimmermann@tugraz.at>
License-Expression: GPL-3.0-or-later
Project-URL: Repository, https://gitlab.tugraz.at/BA9D3CA475A1A669/auditory_models.git
Keywords: audio,quality,speech,perception,intelligibility,model,auditory,stoi,gpsm,snr
Classifier: Development Status :: 4 - Beta
Classifier: Intended Audience :: Science/Research
Classifier: Operating System :: Microsoft :: Windows :: Windows 10
Classifier: Programming Language :: Python :: 3.12
Classifier: Topic :: Scientific/Engineering
Requires-Python: >=3.12
License-File: COPYING
Requires-Dist: numpy>=2.2
Requires-Dist: scipy>=1.15
Requires-Dist: soundfile
Dynamic: license-file
